fgi_yaml_formattor-0.1.1.post0.dist-info/METADATA
fgi_yaml_formattor-0.1.1.post0.dist-info/WHEEL
fgi_yaml_formattor-0.1.1.post0.dist-info/entry_points.txt
fgi_yaml_formattor-0.1.1.post0.dist-info/licenses/LICENSE
fgi_yaml_formattor/__init__.py
fgi_yaml_formattor-0.1.1.post0.dist-info/RECORD
